akerbp/mlops/__init__.py
akerbp/mlops/_version.py
akerbp/mlops/cdf/__init__.py
akerbp/mlops/cdf/handler.py
akerbp/mlops/cdf/helpers.py
akerbp/mlops/core/__init__.py
akerbp/mlops/core/config.py
akerbp/mlops/core/exceptions.py
akerbp/mlops/core/helpers.py
akerbp/mlops/core/logger.py
akerbp/mlops/core/logger_config.py
akerbp/mlops/core/mappings.py
akerbp/mlops/deployment/__init__.py
akerbp/mlops/deployment/actions/deploy-prediction-service-action/action.yml
akerbp/mlops/deployment/actions/setup-mlops-action/action.yml
akerbp/mlops/deployment/deploy.py
akerbp/mlops/deployment/deploy_prediction_service.py
akerbp/mlops/deployment/deploy_training_service.py
akerbp/mlops/deployment/helpers.py
akerbp/mlops/deployment/main.yml
akerbp/mlops/deployment/platforms.py
akerbp/mlops/deployment/setup.py
akerbp/mlops/model_manager/__init__.py
akerbp/mlops/model_manager/model_manager.py
akerbp/mlops/pipeline_helpers/promote_artifacts.py
akerbp/mlops/pipeline_helpers/tag_commit.sh
akerbp/mlops/pipeline_helpers/tag_model_version.py
akerbp/mlops/services/__init__.py
akerbp/mlops/services/prediction.py
akerbp/mlops/services/test_service.py
akerbp/mlops/services/training.py
akerbp_mlops-4.0.0.dist-info/LICENSE
akerbp_mlops-4.0.0.dist-info/METADATA
akerbp_mlops-4.0.0.dist-info/WHEEL
akerbp_mlops-4.0.0.dist-info/entry_points.txt
akerbp_mlops-4.0.0.dist-info/RECORD
