Metadata-Version: 2.1
Name: akerbp-mlops
Version: 4.0.0
Summary: AkerBP MLOps framework
Home-page: https://github.com/AkerBP/expres-ml-mlops
License: Apache-2.0
Author: Alfonso M. Canterla
Author-email: alfonso.canterla@soprasteria.com
Maintainer: Christian N. Lehre
Maintainer-email: christian.lehre@akerbp.com
Requires-Python: >=3.9,<4.0
Classifier: License :: OSI Approved :: Apache Software License
Classifier: Programming Language :: Python :: 3
Classifier: Programming Language :: Python :: 3.9
Classifier: Programming Language :: Python :: 3.10
Classifier: Programming Language :: Python :: 3.11
Classifier: Programming Language :: Python :: 3.12
Provides-Extra: cdf
Requires-Dist: PyYAML (>=5.4.1)
Requires-Dist: cognite-sdk[pandas] (>=4.4.3,<6) ; extra == "cdf"
Requires-Dist: packaging (>=23.2,<24.0)
Requires-Dist: pydantic (>=1.7.3,<2)
Requires-Dist: pytest (>=7.4.3,<8.0.0)
Project-URL: Repository, https://github.com/AkerBP/expres-ml-mlops
Project-URL: Tracker, https://github.com/AkerBP/expres-ml-mlops/issues
